pyDendron/__init__.py
pyDendron/__main__.py
pyDendron/app_logger.py
pyDendron/componentsTree.py
pyDendron/crossdating.py
pyDendron/dataname.py
pyDendron/dataset.py
pyDendron/detrend.py
pyDendron/estimation.py
pyDendron/indices_aligments.py
pyDendron/mean.py
pyDendron/ploter.py
pyDendron/pyDendron_panel.py
pyDendron/pyDendron_pyodide.py
pyDendron/alien/dccd.py
pyDendron/alien/io.py
pyDendron/alien/io_besancon.py
pyDendron/alien/io_dendronIV.py
pyDendron/alien/io_heidelberg.py
pyDendron/alien/io_rwl.py
pyDendron/alien/io_sylphe.py
pyDendron/alien/io_tridas.py
pyDendron/alien/irtdb.py
pyDendron/alien/mdb2csv.py
pyDendron/data/dataset_test.p
pyDendron/data/trees.svg
pyDendron/data/trees_blue.svg
pyDendron/gui_panel/crossdating_panel.py
pyDendron/gui_panel/dataset_package.py
pyDendron/gui_panel/dataset_package_builder.py
pyDendron/gui_panel/dataset_package_editor.py
pyDendron/gui_panel/dataset_selector.py
pyDendron/gui_panel/dataset_treeview.py
pyDendron/gui_panel/debug_panel.py
pyDendron/gui_panel/dialog.py
pyDendron/gui_panel/my_viewer.py
pyDendron/gui_panel/ploter_panel.py
pyDendron/gui_panel/run.py
pyDendron/gui_panel/sidebar.py
pyDendron/gui_panel/tabulator.py
pyDendron/gui_panel/tools_panel.py
pyDendron/tools/alignment.py
pyDendron/tools/dplpy.py
pyDendron/tools/location.py
pyDendron-1.7.5.dist-info/METADATA
pyDendron-1.7.5.dist-info/WHEEL
pyDendron-1.7.5.dist-info/entry_points.txt
pyDendron-1.7.5.dist-info/top_level.txt
pyDendron-1.7.5.dist-info/RECORD
