Metadata-Version: 2.1
Name: pyDendron
Version: 1.7.5
Summary: Open-source python package dedicated to dendrochronology
Author-email: Sylvain Meignier <sylvain.meignier@univ-lemans.fr>
License: GNU GENERAL PUBLIC LICENSE
Project-URL: Homepage, https://git-lium.univ-lemans.fr/Meignier/pyDendron
Classifier: Development Status :: 3 - Alpha
Classifier: Programming Language :: Python :: 3
Classifier: License :: OSI Approved :: GNU General Public License v3 (GPLv3)
Classifier: Operating System :: OS Independent
Classifier: Environment :: Web Environment
Classifier: Intended Audience :: Science/Research
Requires-Python: >=3.9
Requires-Dist: numpy
Requires-Dist: pandas
Requires-Dist: panel>=1.5.2
Requires-Dist: matplotlib
Requires-Dist: scipy
Requires-Dist: xlsxwriter
Requires-Dist: scikit-learn
Requires-Dist: seaborn
Requires-Dist: statsmodels
Requires-Dist: networkx
Requires-Dist: lxml
Requires-Dist: csaps
Requires-Dist: numba
Requires-Dist: ipywidgets-bokeh
